{
  "entities": [
    {
      "name": "env_sun_light",
      "components": [
        {
          "name": "light",
          "parameters": {
            "type": "direct",
            "direction": [ 0.4, -0.3, -0.5 ],
            "color": [ 0.79, 0.78, 0.68, 1.2 ],
            "ambient_color": [ 0.66, 0.68, 0.70, 0.8 ]
          }
        }
      ]
    },
    {
      "name": "env_wind",
      "components": [
        {
          "name": "wind",
          "parameters": {
            "type": "direct",
            "direction": [ 0.0, 0.0, 1.0 ],
            "power": 1.9
          }
        }
      ]
    },
    {
      "name": "env_flat_height_map",
      "components": [
        {
          "name": "height_map",
          "parameters": {
            "heightmap": "flat_height_map"
          }
        },
        {
          "name": "rigid_static",
          "parameters": {}
        }
      ]
    }
  ]
}